windowsort/__init__.py
windowsort/colors.py
windowsort/datahandler.py
windowsort/drift.py
windowsort/gui.py
windowsort/snapshot.py
windowsort/spikes.py
windowsort/threshold.py
windowsort/timeamplitudewindow.py
windowsort/units.py
windowsort/voltage.py
windowsort-0.2.1.dist-info/METADATA
windowsort-0.2.1.dist-info/WHEEL
windowsort-0.2.1.dist-info/entry_points.txt
windowsort-0.2.1.dist-info/top_level.txt
windowsort-0.2.1.dist-info/RECORD
