Metadata-Version: 2.1
Name: windowsort
Version: 0.2.1
Home-page: https://github.com/EdConnorLab/WindowSort
Author: Allen Chen
Author-email: allenmuhanchen@gmail.com
Requires-Dist: appdirs ~=1.4.4
Requires-Dist: ConnorLabAnalysisTools ~=0.2.2
Requires-Dist: numpy >=1.26.1
Requires-Dist: PyQt5 ~=5.15.10
Requires-Dist: PyQt5-sip ~=12.13.0
Requires-Dist: pyqtgraph ~=0.13.3
Requires-Dist: scipy ~=1.13.0
Requires-Dist: setuptools ==68.0.0
